mariadb_composition/__init__.py
mariadb_composition/py.typed
mariadb_composition-1.0.0.dist-info/METADATA
mariadb_composition-1.0.0.dist-info/WHEEL
mariadb_composition-1.0.0.dist-info/licenses/LICENSE
mariadb_composition-1.0.0.dist-info/RECORD
