Metadata-Version: 2.3
Name: mariadb_composition
Version: 1.0.0
Summary: SQL String Composition for MariaDB
Project-URL: Homepage, https://github.com/jarrodlombardo/mariadb-composition
Project-URL: Issues, https://github.com/jarrodlombardo/mariadb-composition/issues
Author-email: Jarrod Lombardo <jarrodl@gmail.com>
License-File: LICENSE
Classifier: License :: OSI Approved :: MIT License
Classifier: Operating System :: OS Independent
Classifier: Programming Language :: Python :: 3
Requires-Python: >=3.12
